odoo/addons/budget_activity_advance_clearing/README.rst
odoo/addons/budget_activity_advance_clearing/__init__.py
odoo/addons/budget_activity_advance_clearing/__manifest__.py
odoo/addons/budget_activity_advance_clearing/data/budget_advance_data.xml
odoo/addons/budget_activity_advance_clearing/models/__init__.py
odoo/addons/budget_activity_advance_clearing/models/base_budget_move.py
odoo/addons/budget_activity_advance_clearing/models/budget_activity.py
odoo/addons/budget_activity_advance_clearing/models/budget_control.py
odoo/addons/budget_activity_advance_clearing/models/budget_period.py
odoo/addons/budget_activity_advance_clearing/models/hr_expense.py
odoo/addons/budget_activity_advance_clearing/readme/CONFIGURE.md
odoo/addons/budget_activity_advance_clearing/readme/CONTRIBUTORS.md
odoo/addons/budget_activity_advance_clearing/readme/DESCRIPTION.md
odoo/addons/budget_activity_advance_clearing/readme/USAGE.md
odoo/addons/budget_activity_advance_clearing/static/description/icon.png
odoo/addons/budget_activity_advance_clearing/static/description/index.html
odoo/addons/budget_activity_advance_clearing/tests/__init__.py
odoo/addons/budget_activity_advance_clearing/tests/test_budget_activity_advance.py
odoo/addons/budget_activity_advance_clearing/views/advance_budget_move.xml
odoo/addons/budget_activity_advance_clearing/views/hr_expense_view.xml
odoo_addon_budget_activity_advance_clearing-18.0.1.0.1.dist-info/METADATA
odoo_addon_budget_activity_advance_clearing-18.0.1.0.1.dist-info/WHEEL
odoo_addon_budget_activity_advance_clearing-18.0.1.0.1.dist-info/top_level.txt
odoo_addon_budget_activity_advance_clearing-18.0.1.0.1.dist-info/RECORD
